icy/__init__.py
icy/client.py
icy/models.py
icyex_stl-1.0.0.dist-info/licenses/LICENSE
icyex_stl-1.0.0.dist-info/METADATA
icyex_stl-1.0.0.dist-info/WHEEL
icyex_stl-1.0.0.dist-info/top_level.txt
icyex_stl-1.0.0.dist-info/RECORD
