Metadata-Version: 2.4
Name: icyex-sTL
Version: 1.0.0
Summary: Telegram User Information Extractor with Advanced Risk Analysis
Home-page: https://github.com/hunter_sfcb/icyex-sTL
Author: IcyEx
Author-email: hunter <m.sajjadd89@gmail.com>
Maintainer: hunter
Maintainer-email: hunter <m.sajjadd89@gmail.com>
License: MIT
Project-URL: Homepage, https://github.com/icyex/icyex-sTL
Project-URL: Documentation, https://icyex-stl.readthedocs.io
Project-URL: Repository, https://github.com/icyex/icyex-sTL
Project-URL: Bug Tracker, https://github.com/icyex/icyex-sTL/issues
Project-URL: Changelog, https://github.com/icyex/icyex-sTL/blob/main/CHANGELOG.md
Keywords: telegram,telegram-bot,user-info,user-extractor,risk-analysis,security,analytics,bot,api,telegram-api,user-verification,account-analysis
Platform: any
Classifier: Development Status :: 5 - Production/Stable
Classifier: Intended Audience :: Developers
Classifier: Topic :: Software Development :: Libraries :: Python Modules
Classifier: Topic :: Communications :: Chat
Classifier: Topic :: Internet
Classifier: Topic :: Security
Classifier: License :: OSI Approved :: MIT License
Classifier: Programming Language :: Python :: 3
Classifier: Programming Language :: Python :: 3.7
Classifier: Programming Language :: Python :: 3.8
Classifier: Programming Language :: Python :: 3.9
Classifier: Programming Language :: Python :: 3.10
Classifier: Programming Language :: Python :: 3.11
Classifier: Programming Language :: Python :: 3.12
Classifier: Operating System :: OS Independent
Classifier: Natural Language :: English
Classifier: Typing :: Typed
Requires-Python: >=3.7
License-File: LICENSE
Requires-Dist: python-telegram-bot<21.0,>=20.0
Requires-Dist: requests<3.0.0,>=2.25.0
Provides-Extra: dev
Requires-Dist: pytest>=7.0.0; extra == "dev"
Requires-Dist: pytest-asyncio>=0.21.0; extra == "dev"
Requires-Dist: pytest-cov>=4.0.0; extra == "dev"
Requires-Dist: black>=23.0.0; extra == "dev"
Requires-Dist: flake8>=6.0.0; extra == "dev"
Requires-Dist: mypy>=1.0.0; extra == "dev"
Requires-Dist: isort>=5.12.0; extra == "dev"
Requires-Dist: pre-commit>=3.0.0; extra == "dev"
Provides-Extra: docs
Requires-Dist: sphinx>=6.0.0; extra == "docs"
Requires-Dist: sphinx-rtd-theme>=1.2.0; extra == "docs"
Requires-Dist: sphinx-autodoc-typehints>=1.22.0; extra == "docs"
Provides-Extra: test
Requires-Dist: pytest>=7.0.0; extra == "test"
Requires-Dist: pytest-asyncio>=0.21.0; extra == "test"
Requires-Dist: pytest-cov>=4.0.0; extra == "test"
Requires-Dist: coverage>=7.0.0; extra == "test"
Dynamic: author
Dynamic: home-page
Dynamic: license-file
Dynamic: requires-python
